lionshare/__init__.py
lionshare/lionshareapi.py
lionshare-1.0.2.dist-info/LICENSE.txt
lionshare-1.0.2.dist-info/METADATA
lionshare-1.0.2.dist-info/RECORD
lionshare-1.0.2.dist-info/WHEEL
lionshare-1.0.2.dist-info/top_level.txt
